python_pptx_text_replacer/TextReplacer.py
python_pptx_text_replacer/__init__.py
python_pptx_text_replacer/__main__.py
python_pptx_text_replacer-0.0.5.post0.dist-info/METADATA
python_pptx_text_replacer-0.0.5.post0.dist-info/WHEEL
python_pptx_text_replacer-0.0.5.post0.dist-info/entry_points.txt
python_pptx_text_replacer-0.0.5.post0.dist-info/licenses/LICENSE
python_pptx_text_replacer-0.0.5.post0.dist-info/RECORD
