Metadata-Version: 2.1
Name: python-pptx-text-replacer
Version: 0.0.5.post0
Summary: This package implements text replacement in Powerpoint files in pptx format.
Project-URL: Homepage, https://github.com/fschaeck/python-pptx-text-replacer
Project-URL: Bug Tracker, https://github.com/fschaeck/python-pptx-text-replacer/issues
Author-email: Frank Schäckermann <pypi-fschaeckermann@snkmail.com>
Keywords: PowerPoint,Text Replacement,pptx
Classifier: Development Status :: 3 - Alpha
Classifier: Environment :: Console
Classifier: Intended Audience :: End Users/Desktop
Classifier: License :: OSI Approved :: GNU General Public License v3 (GPLv3)
Classifier: Operating System :: OS Independent
Classifier: Programming Language :: Python :: 2.7
Classifier: Programming Language :: Python :: 3
Classifier: Topic :: Utilities
Requires-Python: >=2.7
Requires-Dist: python-pptx
